sparkdl/__init__.py
sparkdl/estimators/__init__.py
sparkdl/estimators/keras_image_file_estimator.py
sparkdl/estimators/msg_queue.py
sparkdl/estimators/text_estimator.py
sparkdl/exmaples/TFoSExample.py
sparkdl/exmaples/__init__.py
sparkdl/exmaples/sk_learn_example.py
sparkdl/graph/__init__.py
sparkdl/graph/builder.py
sparkdl/graph/pieces.py
sparkdl/graph/tensorframes_udf.py
sparkdl/graph/utils.py
sparkdl/image/__init__.py
sparkdl/image/imageIO.py
sparkdl/nlp/__init__.py
sparkdl/nlp/text_analysis.py
sparkdl/nlp/model/__init__.py
sparkdl/nlp/model/text_cnn.py
sparkdl/param/__init__.py
sparkdl/param/image_params.py
sparkdl/param/shared_params.py
sparkdl/tf/__init__.py
sparkdl/tf/focal_loss.py
sparkdl/transformers/__init__.py
sparkdl/transformers/easy_feature.py
sparkdl/transformers/keras_applications.py
sparkdl/transformers/keras_image.py
sparkdl/transformers/keras_utils.py
sparkdl/transformers/named_image.py
sparkdl/transformers/tf_image.py
sparkdl/transformers/tf_text.py
sparkdl/transformers/utils.py
sparkdl/udf/__init__.py
sparkdl/udf/keras_image_model.py
sparkdl/utils/__init__.py
sparkdl/utils/jvmapi.py
sparkdl/utils/keras_model.py
sparkdl-0.2.2.dist-info/METADATA
sparkdl-0.2.2.dist-info/RECORD
sparkdl-0.2.2.dist-info/WHEEL
sparkdl-0.2.2.dist-info/top_level.txt
tests/TFoSBaseSparkTest.py
tests/__init__.py
tests/tests.py
tests/estimators/__init__.py
tests/estimators/test_keras_estimators.py
tests/graph/__init__.py
tests/graph/test_builder.py
tests/graph/test_pieces.py
tests/image/__init__.py
tests/image/test_imageIO.py
tests/transformers/__init__.py
tests/transformers/image_utils.py
tests/transformers/keras_image_test.py
tests/transformers/named_image_InceptionV3_test.py
tests/transformers/named_image_ResNet50_test.py
tests/transformers/named_image_Xception_test.py
tests/transformers/named_image_test.py
tests/transformers/tf_image_test.py
tests/transformers/tf_text_test.py
tests/udf/__init__.py
tests/udf/keras_sql_udf_test.py
tests/utils/__init__.py
tests/utils/test_python_interface.py
